Orange3_ImageAnalytics-0.13.0-py3.11-nspkg.pth
Orange3_ImageAnalytics-0.13.0.data/data/help/orange3-imageanalytics/.buildinfo
Orange3_ImageAnalytics-0.13.0.data/data/help/orange3-imageanalytics/genindex.html
Orange3_ImageAnalytics-0.13.0.data/data/help/orange3-imageanalytics/index.html
Orange3_ImageAnalytics-0.13.0.data/data/help/orange3-imageanalytics/objects.inv
Orange3_ImageAnalytics-0.13.0.data/data/help/orange3-imageanalytics/search.html
Orange3_ImageAnalytics-0.13.0.data/data/help/orange3-imageanalytics/searchindex.js
Orange3_ImageAnalytics-0.13.0.data/data/help/orange3-imageanalytics/_images/ImageEmbedding-Example1.png
Orange3_ImageAnalytics-0.13.0.data/data/help/orange3-imageanalytics/_images/ImageEmbedding-Example2.png
Orange3_ImageAnalytics-0.13.0.data/data/help/orange3-imageanalytics/_images/ImageEmbedding-stamped.png
Orange3_ImageAnalytics-0.13.0.data/data/help/orange3-imageanalytics/_images/ImageGrid-Example.png
Orange3_ImageAnalytics-0.13.0.data/data/help/orange3-imageanalytics/_images/ImageGrid-stamped.png
Orange3_ImageAnalytics-0.13.0.data/data/help/orange3-imageanalytics/_images/ImageViewer-stamped.png
Orange3_ImageAnalytics-0.13.0.data/data/help/orange3-imageanalytics/_images/ImportImages-Example.png
Orange3_ImageAnalytics-0.13.0.data/data/help/orange3-imageanalytics/_images/ImportImages-class.png
Orange3_ImageAnalytics-0.13.0.data/data/help/orange3-imageanalytics/_images/ImportImages-stamped.png
Orange3_ImageAnalytics-0.13.0.data/data/help/orange3-imageanalytics/_images/SaveImages-Example.png
Orange3_ImageAnalytics-0.13.0.data/data/help/orange3-imageanalytics/_images/SaveImages.png
Orange3_ImageAnalytics-0.13.0.data/data/help/orange3-imageanalytics/_images/header-example.png
Orange3_ImageAnalytics-0.13.0.data/data/help/orange3-imageanalytics/_images/image-viewer-example1.png
Orange3_ImageAnalytics-0.13.0.data/data/help/orange3-imageanalytics/_images/image-viewer-example2.png
Orange3_ImageAnalytics-0.13.0.dist-info/LICENSE.txt
Orange3_ImageAnalytics-0.13.0.dist-info/METADATA
Orange3_ImageAnalytics-0.13.0.dist-info/WHEEL
Orange3_ImageAnalytics-0.13.0.dist-info/entry_points.txt
Orange3_ImageAnalytics-0.13.0.dist-info/namespace_packages.txt
Orange3_ImageAnalytics-0.13.0.dist-info/top_level.txt
Orange3_ImageAnalytics-0.13.0.dist-info/RECORD
