Metadata-Version: 2.1
Name: Orange3-ImageAnalytics
Version: 0.13.0
Summary: Orange3 add-on for image data mining.
Home-page: http://orange.biolab.si/download
Author: Bioinformatics Laboratory, FRI UL
Author-email: contact@orange.biolab.si
License: GPL3+
Keywords: orange3 add-on,orange3-imageanalytics
Classifier: Development Status :: 1 - Planning
Classifier: Intended Audience :: Education
Classifier: Intended Audience :: Science/Research
Classifier: License :: OSI Approved :: GNU General Public License v3 or later (GPLv3+)
Classifier: Programming Language :: Python :: 3 :: Only
License-File: LICENSE.txt
Requires-Dist: AnyQt
Requires-Dist: ndf>=0.1.4
Requires-Dist: numpy>=1.16
Requires-Dist: Orange3>=3.35.0
Requires-Dist: orange-canvas-core>=0.2.2
Requires-Dist: orange-widget-base>=4.23.0
Requires-Dist: pillow>=6.2.0
Requires-Dist: requests
Requires-Dist: requests-cache
Requires-Dist: scipy
Provides-Extra: doc
Requires-Dist: sphinx; extra == "doc"
Requires-Dist: recommonmark; extra == "doc"
Requires-Dist: sphinx-rtd-theme; extra == "doc"
Provides-Extra: test
Requires-Dist: coverage; extra == "test"
